llama_index/server/__init__.py
llama_index/server/chat_ui.py
llama_index/server/prompts.py
llama_index/server/server.py
llama_index/server/settings.py
llama_index/server/api/__init__.py
llama_index/server/api/models.py
llama_index/server/api/callbacks/__init__.py
llama_index/server/api/callbacks/agent_call_tool.py
llama_index/server/api/callbacks/artifact_transform.py
llama_index/server/api/callbacks/base.py
llama_index/server/api/callbacks/llamacloud.py
llama_index/server/api/callbacks/source_nodes.py
llama_index/server/api/callbacks/stream_handler.py
llama_index/server/api/callbacks/suggest_next_questions.py
llama_index/server/api/routers/__init__.py
llama_index/server/api/routers/chat.py
llama_index/server/api/routers/dev.py
llama_index/server/api/routers/ui.py
llama_index/server/api/utils/__init__.py
llama_index/server/api/utils/chat_attachments.py
llama_index/server/api/utils/chat_request.py
llama_index/server/api/utils/vercel_stream.py
llama_index/server/gen_ui/__init__.py
llama_index/server/gen_ui/main.py
llama_index/server/gen_ui/parse_workflow_code.py
llama_index/server/models/__init__.py
llama_index/server/models/artifacts.py
llama_index/server/models/chat.py
llama_index/server/models/file.py
llama_index/server/models/hitl.py
llama_index/server/models/source_nodes.py
llama_index/server/models/ui.py
llama_index/server/resources/__init__.py
llama_index/server/resources/ui/404.html
llama_index/server/resources/ui/config.js
llama_index/server/resources/ui/favicon.ico
llama_index/server/resources/ui/index.html
llama_index/server/resources/ui/index.txt
llama_index/server/resources/ui/llama.png
llama_index/server/resources/ui/_next/static/chunks/059e1b7c.5612461df7bf6260.js
llama_index/server/resources/ui/_next/static/chunks/1061.ecf1b2221ed34359.js
llama_index/server/resources/ui/_next/static/chunks/1128.9ba97a31432579ba.js
llama_index/server/resources/ui/_next/static/chunks/1280.4da63da937283e4f.js
llama_index_server-0.1.27.dist-info/METADATA
llama_index_server-0.1.27.dist-info/WHEEL
llama_index_server-0.1.27.dist-info/RECORD
