Metadata-Version: 2.4
Name: llama-index-server
Version: 0.1.27
Summary: llama-index fastapi server
Author-email: Your Name <you@example.com>
License-Expression: MIT
Requires-Python: <4.0,>=3.9
Requires-Dist: cachetools<6.0.0,>=5.5.2
Requires-Dist: fastapi[standard]<1.0.0,>=0.115.11
Requires-Dist: llama-index-core<1.0.0,>=0.12.28
Requires-Dist: llama-index-indices-managed-llama-cloud<1.0.0,>=0.6.3
Requires-Dist: llama-index-readers-file<1.0.0,>=0.4.6
Requires-Dist: pydantic-settings<3.0.0,>=2.8.1
Requires-Dist: requests<3.0.0,>=2.32.3
